embeddings_explorer/__init__.py
embeddings_explorer/corpus/__init__.py
embeddings_explorer/corpus/brown_corpus_provider.py
embeddings_explorer/corpus/corpus_provider.py
embeddings_explorer/corpus/food_corpus_provider.py
embeddings_explorer/graph/__init__.py
embeddings_explorer/graph/bfs_traverser.py
embeddings_explorer/graph/graph_constructor.py
embeddings_explorer/graph/knn_graph.py
embeddings_explorer/graph/traverser.py
embeddings_explorer/graph/weighted_traverser.py
embeddings_explorer/models/__init__.py
embeddings_explorer/models/bert.py
embeddings_explorer/models/generator.py
embeddings_explorer/models/openai.py
embeddings_explorer/models/sentence_bert.py
embeddings_explorer/models/voyage.py
embeddings_explorer/orchestrator/__init__.py
embeddings_explorer/orchestrator/explorer.py
embeddings_explorer/utils/__init__.py
embeddings_explorer/utils/cache.py
tests/__init__.py
tests/test_generators.py
embeddings_explorer-0.1.2.dist-info/LICENSE
embeddings_explorer-0.1.2.dist-info/METADATA
embeddings_explorer-0.1.2.dist-info/WHEEL
embeddings_explorer-0.1.2.dist-info/top_level.txt
embeddings_explorer-0.1.2.dist-info/RECORD
